{"errors":[],"warnings":[],"version":"2.1.0-beta.4","hash":"f4e4ef4fe174446670db","publicPath":"/dist/static/","assetsByChunkName":{"vendor":"vendor.js?cdb104980566edc955f0","main":["main.js?f9f6ca96b25fb184d8b2","main.css?f19d70f4e53a30c45606df16c6e83477"]},"assets":[{"name":"vendor.js?cdb104980566edc955f0","size":2360143,"chunks":[0],"chunkNames":["vendor"],"emitted":true},{"name":"1.clientchunk.js?29705b078bd0426670e5","size":16611,"chunks":[1],"chunkNames":[],"emitted":true},{"name":"2.clientchunk.js?6d27a9217e87b56fe9de","size":12075,"chunks":[2],"chunkNames":[],"emitted":true},{"name":"main.js?f9f6ca96b25fb184d8b2","size":1618538,"chunks":[3],"chunkNames":["main"],"emitted":true},{"name":"main.css?f19d70f4e53a30c45606df16c6e83477","size":41,"chunks":[3],"chunkNames":["main"],"emitted":true},{"name":"../../../webpack-stats.json","size":0,"chunks":[],"chunkNames":[]}],"children":[{"errors":[],"warnings":[],"publicPath":"/dist/static/","assetsByChunkName":{},"assets":[],"children":[],"name":"extract-text-webpack-plugin"}]}